agents/__init__.py
agents/analysis_agent.py
agents/base_agent.py
agents/coordinator_agent.py
agents/generation_agent.py
agents/optimization_agent.py
agents/validation_agent.py
ai/__init__.py
ai/ai_optimizer.py
ai/context_manager.py
ai/llm_factory.py
ai/llm_manager.py
ai/prompt_engineer.py
analyzers/__init__.py
analyzers/code_analyzer.py
analyzers/dependency_analyzer.py
analyzers/project_analyzer.py
cli/__init__.py
cli/config_cli.py
cli/interactive_cli.py
cli/main.py
cli/multi_agent_cli.py
cli/simple_cli.py
config/environment.py
config/global_config.py
generators/__init__.py
generators/code_generator.py
generators/template_generator.py
generators/test_generator.py
ia_agent_dotnet-0.10.0.dist-info/licenses/LICENSE
langchain_agents/memory/__init__.py
langchain_agents/memory/conversation_memory.py
langchain_agents/memory/vector_memory.py
langchain_agents/reasoning/__init__.py
langchain_agents/reasoning/planning_agent.py
langchain_agents/reasoning/react_agent.py
langchain_agents/reasoning/reasoning_chain.py
memory/memory_manager.py
monitoring/__init__.py
monitoring/dashboard.py
monitoring/metrics_collector.py
monitoring/performance_monitor.py
monitoring/performance_optimizer.py
monitoring/quality_analyzer.py
multi_agent/__init__.py
multi_agent/autogen_collaboration.py
multi_agent/shared_memory.py
tools/__init__.py
tools/dotnet_tools.py
tools/file_tools.py
tools/memory_analysis_tools.py
utils/__init__.py
utils/chromadb_singleton.py
utils/config.py
utils/config_validator.py
utils/error_handler.py
utils/helpers.py
utils/logging.py
utils/version_checker.py
ia_agent_dotnet-0.10.0.dist-info/METADATA
ia_agent_dotnet-0.10.0.dist-info/WHEEL
ia_agent_dotnet-0.10.0.dist-info/entry_points.txt
ia_agent_dotnet-0.10.0.dist-info/top_level.txt
ia_agent_dotnet-0.10.0.dist-info/RECORD
