Metadata-Version: 2.4
Name: ia-agent-dotnet
Version: 0.10.0
Summary: IA Agent para Generación de Pruebas Unitarias .NET - Sistema multi-agente inteligente
Home-page: https://github.com/Lopand-Solutions/ia-agent-to-unit-test-api-rest
Author: Paulo Andrade
Author-email: Paulo Andrade <paulo_866@hotmail.com>
License: MIT
Project-URL: Homepage, https://github.com/Lopand-Solutions/ia-agent-to-unit-test-api-rest
Project-URL: Repository, https://github.com/Lopand-Solutions/ia-agent-to-unit-test-api-rest
Project-URL: Documentation, https://github.com/Lopand-Solutions/ia-agent-to-unit-test-api-rest/blob/develop/docs/USER_GUIDE.md
Project-URL: Bug Tracker, https://github.com/Lopand-Solutions/ia-agent-to-unit-test-api-rest/issues
Keywords: ai,agent,dotnet,testing,unit-tests,langchain,openai,deepseek,gemini,automation,code-generation
Classifier: Development Status :: 4 - Beta
Classifier: Intended Audience :: Developers
Classifier: Topic :: Software Development :: Testing
Classifier: Topic :: Software Development :: Quality Assurance
Classifier: License :: OSI Approved :: MIT License
Classifier: Programming Language :: Python :: 3
Classifier: Programming Language :: Python :: 3.11
Classifier: Programming Language :: Python :: 3.12
Classifier: Operating System :: OS Independent
Requires-Python: >=3.11
License-File: LICENSE
Requires-Dist: langchain>=0.1.0
Requires-Dist: langchain-openai>=0.0.5
Requires-Dist: langchain-community>=0.0.10
Requires-Dist: langchain-google-genai>=1.0.0
Requires-Dist: langchain-anthropic>=0.1.0
Requires-Dist: pyautogen>=0.2.0
Requires-Dist: openai>=1.3.0
Requires-Dist: anthropic>=0.7.0
Requires-Dist: google-generativeai>=0.3.0
Requires-Dist: chromadb>=0.4.0
Requires-Dist: faiss-cpu>=1.7.4
Requires-Dist: sentence-transformers>=2.2.2
Requires-Dist: numpy>=1.24.0
Requires-Dist: click>=8.0.0
Requires-Dist: rich>=13.0.0
Requires-Dist: pydantic>=2.0.0
Requires-Dist: pydantic-settings>=2.0.0
Requires-Dist: pyyaml>=6.0
Requires-Dist: loguru>=0.7.0
Requires-Dist: structlog>=23.2.0
Requires-Dist: psutil>=5.9.0
Requires-Dist: python-dotenv>=1.0.0
Requires-Dist: tqdm>=4.65.0
Requires-Dist: requests>=2.31.0
Requires-Dist: aiohttp>=3.8.0
Requires-Dist: asyncio>=3.4.3
Requires-Dist: typing-extensions>=4.5.0
Provides-Extra: dev
Requires-Dist: pytest>=7.0.0; extra == "dev"
Requires-Dist: pytest-asyncio>=0.21.0; extra == "dev"
Requires-Dist: black>=23.0.0; extra == "dev"
Requires-Dist: flake8>=6.0.0; extra == "dev"
Requires-Dist: mypy>=1.0.0; extra == "dev"
Provides-Extra: docs
Requires-Dist: sphinx>=6.0.0; extra == "docs"
Requires-Dist: sphinx-rtd-theme>=1.2.0; extra == "docs"
Dynamic: author
Dynamic: home-page
Dynamic: license-file
Dynamic: requires-python
